LICENSE.txt
MANIFEST.in
README.txt
setup.py
django_urlalternatives.egg-info/PKG-INFO
django_urlalternatives.egg-info/SOURCES.txt
django_urlalternatives.egg-info/dependency_links.txt
django_urlalternatives.egg-info/top_level.txt
urlalternatives/__init__.py
urlalternatives/models.py
urlalternatives/tests.py
urlalternatives/views.py