Metadata-Version: 1.0
Name: django-urlalternatives
Version: 0.1.0
Summary: Django URL alternatives provides a way for dispatching one URL pattern to the first alternative view (callback function) in a list that returns success.
Home-page: http://gw.tnode.com/0483-Django/
Author: GW
Author-email: gw.2011@tnode.com
License: LICENSE.txt
Platform: UNKNOWN
